pyqode/language_server/__init__.py
pyqode/language_server/backend/__init__.py
pyqode/language_server/backend/server.py
pyqode/language_server/backend/workers.py
pyqode/language_server/modes/__init__.py
pyqode/language_server/modes/calltips.py
pyqode/language_server/modes/diagnostics.py
pyqode/language_server/modes/language_server_mode.py
pyqode/language_server/modes/symbols.py
pyqode_language_server-0.2.3.dist-info/LICENSE
pyqode_language_server-0.2.3.dist-info/WHEEL
pyqode_language_server-0.2.3.dist-info/METADATA
pyqode_language_server-0.2.3.dist-info/RECORD
