Metadata-Version: 2.1
Name: pyqode.language-server
Version: 0.2.3
Summary: pyqode.language_server is an extension of pyqode.core that brings support
Keywords: CodeEdit,PyQt,editor,lsp,language-server
Author-email: Sebastiaan Mathôt <s.mathot@cogsci.nl>
Requires-Python: >=3.7
Project-URL: Documentation, https://rapunzel.cogsci.nl/manual/language-server/
Project-URL: Source, https://github.com/open-cogsci/pyqode.language_server
